LICENSE
NOTICE
README.md
apache_liminal-0.0.5.data/scripts/liminal
liminal/__init__.py
liminal/settings.py
liminal/build/__init__.py
liminal/build/image_builder.py
liminal/build/liminal_apps_builder.py
liminal/build/python.py
liminal/build/image/__init__.py
liminal/build/image/python/Dockerfile
liminal/build/image/python/__init__.py
liminal/build/image/python/python.py
liminal/build/image/python_server/Dockerfile
liminal/build/image/python_server/__init__.py
liminal/build/image/python_server/liminal_python_server.py
liminal/build/image/python_server/python_server.py
liminal/build/image/python_server/python_server_requirements.txt
liminal/build/image/spark/Dockerfile
liminal/build/image/spark/__init__.py
liminal/build/image/spark/spark.py
liminal/core/__init__.py
liminal/core/environment.py
liminal/core/config/__init__.py
liminal/core/config/config.py
liminal/core/config/defaults/__init__.py
liminal/core/config/defaults/default_configs.py
liminal/core/config/defaults/base/__init__.py
liminal/core/config/defaults/base/liminal.yml
liminal/core/util/__init__.py
liminal/core/util/class_util.py
liminal/core/util/dict_util.py
liminal/core/util/env_util.py
liminal/core/util/extensible.py
liminal/core/util/files_util.py
liminal/docker/__init__.py
liminal/kubernetes/__init__.py
liminal/kubernetes/secret_util.py
liminal/kubernetes/volume_util.py
liminal/logging/__init__.py
liminal/logging/logging_setup.py
liminal/monitoring/__init__.py
liminal/runners/__init__.py
liminal/runners/airflow/__init__.py
liminal/runners/airflow/config/__init__.py
liminal/runners/airflow/config/standalone_variable_backend.py
liminal/runners/airflow/dag/__init__.py
liminal/runners/airflow/dag/liminal_dags.py
liminal/runners/airflow/dag/liminal_register_dags.py
liminal/runners/airflow/executors/__init__.py
liminal/runners/airflow/executors/airflow.py
liminal/runners/airflow/executors/emr.py
liminal/runners/airflow/executors/kubernetes.py
liminal/runners/airflow/model/__init__.py
apache_liminal-0.0.5.dist-info/LICENSE
apache_liminal-0.0.5.dist-info/METADATA
apache_liminal-0.0.5.dist-info/NOTICE
apache_liminal-0.0.5.dist-info/WHEEL
apache_liminal-0.0.5.dist-info/top_level.txt
apache_liminal-0.0.5.dist-info/RECORD
