Metadata-Version: 2.1
Name: apache-liminal
Version: 0.0.5
Summary: A package for authoring and deploying machine learning workflows
Home-page: https://github.com/apache/incubator-liminal
Author: dev@liminal.apache.org
Author-email: dev@liminal.apache.org
License: Apache License, Version 2.0
Classifier: Programming Language :: Python :: 3
Classifier: License :: OSI Approved :: Apache Software License
Classifier: Operating System :: OS Independent
Requires-Python: >=3.6
License-File: LICENSE
License-File: NOTICE
Requires-Dist: docker (==4.2.0)
Requires-Dist: apache-airflow (==2.1.2)
Requires-Dist: click (==7.1.1)
Requires-Dist: Flask (==1.1.1)
Requires-Dist: pyyaml (==5.4.1)
Requires-Dist: boto3 (==1.17.112)
Requires-Dist: botocore (==1.20.112)
Requires-Dist: wheel (==0.36.2)
Requires-Dist: termcolor (~=1.1.0)
Requires-Dist: docker-pycreds (==0.4.0)
Requires-Dist: typing (==3.7.4.1)
Requires-Dist: GitPython (==3.1.11)
Requires-Dist: moto (==1.3.14)
Requires-Dist: diskcache (==3.1.1)
Requires-Dist: croniter (==0.3.31)
Requires-Dist: pytz (==2020.5)
Requires-Dist: pytzdata (==2020.1)
Requires-Dist: freezegun (==1.1.0)
Requires-Dist: statsd (<4.0,>=3.3.0)
Requires-Dist: sqlalchemy (~=1.3.15)
Requires-Dist: flatdict (==3.4.0)
Requires-Dist: jinja2 (<2.11.0,>=2.10.1)
Requires-Dist: python-json-logger (==2.0.1)
Requires-Dist: requests (==2.26.0)
Requires-Dist: apache-airflow-providers-amazon (==1.4.0)
Requires-Dist: apache-airflow-providers-cncf-kubernetes (==1.0.2)
Requires-Dist: cfn-lint (==0.53.0)
Requires-Dist: pre-commit (==2.16.0)
Requires-Dist: Werkzeug (==1.0.1)
Requires-Dist: itsdangerous (==1.1.0)
Requires-Dist: MarkupSafe (==1.1.1)
